[
    {
        "_id" : "physics",
        "category" : "science",
        "name" : "Physics",
        "pic" : "./images/physics.jpg"
    },
    {
        "_id" : "chemistry",
        "category" : "science",
        "name" : "Chemistry",
        "pic" : "./images/chemistry.jpg"
    },
    {
        "_id" : "biology",
        "category" : "science",
        "name" : "Biology",
        "pic" : "./images/biology.jpg"
    },
    {
        "_id" : "highermath",
        "category" : "science",
        "name" : "Higher Math",
        "pic" : "./images/highermath.jpg"
    },
    {
        "_id" : "generalmath",
        "category" : "general",
        "name" : "General Math",
        "pic" : "./images/generalmath.jpg"
    },
    {
        "_id" : "bangla-1st",
        "category" : "general",
        "name" : "Bangla Shahitto",
        "pic" : "./images/bangla-1st.jpg"
    },
    {
        "_id" : "english-1st",
        "category" : "general",
        "name" : "English For Today",
        "pic" : "./images/english-1st.jpg"
    },
    {
        "_id" : "religion",
        "category" : "general",
        "name" : "Islam Shikkha",
        "pic" : "./images/religion.jpg"
    },
    {
        "_id" : "social",
        "category" : "general",
        "name" : "B.G.S.",
        "pic" : "./images/social.jpg"
    }
]